mkdocs_copy_markdown/__init__.py
mkdocs_copy_markdown/plugin.py
mkdocs_copy_markdown-0.1.0.dist-info/licenses/LICENSE
mkdocs_copy_markdown-0.1.0.dist-info/METADATA
mkdocs_copy_markdown-0.1.0.dist-info/WHEEL
mkdocs_copy_markdown-0.1.0.dist-info/entry_points.txt
mkdocs_copy_markdown-0.1.0.dist-info/top_level.txt
mkdocs_copy_markdown-0.1.0.dist-info/RECORD
