Metadata-Version: 2.4
Name: mkdocs-copy-markdown
Version: 0.1.0
Summary: An MkDocs plugin that adds a 'Copy as Markdown' button to every page for easy sharing with AI assistants
Author-email: Nathan Drezner <nathan@drezner.xyz>
License-Expression: MIT
Project-URL: Homepage, https://github.com/ndrezn/mkdocs-copy-markdown
Project-URL: Documentation, https://ndrezn.github.io/mkdocs-copy-markdown/
Project-URL: Repository, https://github.com/ndrezn/mkdocs-copy-markdown
Project-URL: Bug Reports, https://github.com/ndrezn/mkdocs-copy-markdown/issues
Keywords: mkdocs,plugin,markdown,copy,clipboard,documentation
Classifier: Development Status :: 4 - Beta
Classifier: Intended Audience :: Developers
Classifier: Operating System :: OS Independent
Classifier: Programming Language :: Python :: 3
Classifier: Programming Language :: Python :: 3.7
Classifier: Programming Language :: Python :: 3.8
Classifier: Programming Language :: Python :: 3.9
Classifier: Programming Language :: Python :: 3.10
Classifier: Programming Language :: Python :: 3.11
Classifier: Programming Language :: Python :: 3.12
Classifier: Topic :: Documentation
Classifier: Topic :: Text Processing
Classifier: Topic :: Software Development :: Documentation
Classifier: Framework :: MkDocs
Requires-Python: >=3.7
License-File: LICENSE
Requires-Dist: mkdocs>=1.0.4
Requires-Dist: mkdocs-material>=9.2.7
Provides-Extra: dev
Requires-Dist: mkdocs-material>=9.0.0; extra == "dev"
Requires-Dist: pytest>=6.0; extra == "dev"
Requires-Dist: pytest-cov; extra == "dev"
Requires-Dist: black; extra == "dev"
Requires-Dist: isort; extra == "dev"
Requires-Dist: flake8; extra == "dev"
Dynamic: license-file
